runsawa/__init__.py
runsawa/runsawa.py
runsawa-0.1.0.dist-info/METADATA
runsawa-0.1.0.dist-info/WHEEL
runsawa-0.1.0.dist-info/licenses/LICENSE
runsawa-0.1.0.dist-info/RECORD
