Metadata-Version: 2.4
Name: runsawa
Version: 0.1.0
Summary: A simple library for running loops concurrently with progress.
Project-URL: Homepage, https://github.com/orasik/runsawa
Project-URL: Bug Tracker, https://github.com/orasik/runsawa/issues
Project-URL: Documentation, https://github.com/orasik/runsawa#readme
Project-URL: Source Code, https://github.com/orasik/runsawa
Author-email: Oras Al-Kubaisi <code@oras.me>
License: MIT License
License-File: LICENSE
Keywords: async,concurrent,parallel,performance,progress,threading
Classifier: License :: OSI Approved :: MIT License
Classifier: Operating System :: OS Independent
Classifier: Programming Language :: Python :: 3
Classifier: Programming Language :: Python :: 3.8
Classifier: Programming Language :: Python :: 3.9
Classifier: Programming Language :: Python :: 3.10
Classifier: Programming Language :: Python :: 3.11
Classifier: Programming Language :: Python :: 3.12
Classifier: Topic :: Internet :: WWW/HTTP
Classifier: Topic :: Software Development :: Libraries :: Python Modules
Classifier: Topic :: System :: Systems Administration
Requires-Python: >=3.8
Requires-Dist: requests
Requires-Dist: tqdm
Provides-Extra: dev
Requires-Dist: black; extra == 'dev'
Requires-Dist: build; extra == 'dev'
Requires-Dist: coverage; extra == 'dev'
Requires-Dist: flake8; extra == 'dev'
Requires-Dist: mypy; extra == 'dev'
Requires-Dist: pytest; extra == 'dev'
Requires-Dist: twine; extra == 'dev'
Provides-Extra: test
Requires-Dist: coverage; extra == 'test'
Requires-Dist: pytest; extra == 'test'
